myuiautomator/__init__.py
myuiautomator/myuiautomator.py
myuiautomator-0.1.dist-info/METADATA
myuiautomator-0.1.dist-info/WHEEL
myuiautomator-0.1.dist-info/top_level.txt
myuiautomator-0.1.dist-info/RECORD
