Metadata-Version: 2.1
Name: myuiautomator
Version: 0.1
Summary: A simple library for Android UI automation using UIAutomator and ADB
Home-page: https://pypi.org/project/myuiautomator/
Author: CodeMaster
Author-email: theloveme400@gmail.com
Classifier: Programming Language :: Python :: 3
Classifier: License :: OSI Approved :: MIT License
Classifier: Operating System :: OS Independent
Requires-Python: >=3.6
Requires-Dist: uiautomator
